s3file/__init__.py
s3file/_version.py
s3file/apps.py
s3file/checks.py
s3file/forms.py
s3file/middleware.py
s3file/storages.py
s3file/storages_optimized.py
s3file/views.py
s3file/static/s3file/js/s3file.js
django_s3file-7.0.0.dist-info/licenses/LICENSE
django_s3file-7.0.0.dist-info/WHEEL
django_s3file-7.0.0.dist-info/METADATA
django_s3file-7.0.0.dist-info/RECORD
