Metadata-Version: 2.4
Name: django-s3file
Version: 7.0.0
Summary: A lightweight file uploader input for Django and Amazon S3.
Author-email: Johannes Maron <johannes@maron.family>
Requires-Python: >=3.11
Classifier: Development Status :: 6 - Mature
Classifier: Environment :: Web Environment
Classifier: Intended Audience :: Developers
Classifier: License :: OSI Approved :: MIT License
Classifier: Operating System :: OS Independent
Classifier: Programming Language :: Python
Classifier: Programming Language :: JavaScript
Classifier: Topic :: Software Development
Classifier: Programming Language :: Python :: 3
Classifier: Programming Language :: Python :: 3 :: Only
Classifier: Programming Language :: Python :: 3.11
Classifier: Programming Language :: Python :: 3.12
Classifier: Programming Language :: Python :: 3.13
Classifier: Framework :: Django
Classifier: Framework :: Django :: 4.2
Classifier: Framework :: Django :: 5.0
Classifier: Framework :: Django :: 5.1
License-File: LICENSE
Requires-Dist: django>=4.2
Requires-Dist: django-storages>=1.6
Requires-Dist: boto3
Project-URL: Changelog, https://github.com/codingjoe/django-s3file/releases
Project-URL: Documentation, https://github.com/codingjoe/django-s3file?tab=readme-ov-file
Project-URL: Funding, https://github.com/sponsors/codingjoe
Project-URL: Homepage, https://github.com/codingjoe/django-s3file
Project-URL: Issues, https://github.com/codingjoe/django-s3file/issues
Project-URL: Releasenotes, https://github.com/codingjoe/django-s3file/releases/latest
Project-URL: Source, https://github.com/codingjoe/django-s3file
